cabinets/__init__.py
cabinets/admin.py
cabinets/api_views.py
cabinets/apps.py
cabinets/forms.py
cabinets/links.py
cabinets/menus.py
cabinets/models.py
cabinets/permissions.py
cabinets/serializers.py
cabinets/urls.py
cabinets/views.py
cabinets/widgets.py
cabinets/compat/__init__.py
cabinets/compat/generics.py
cabinets/compat/managers.py
cabinets/compat/mixins.py
cabinets/compat/tests.py
cabinets/migrations/0001_initial.py
cabinets/migrations/__init__.py
cabinets/static/cabinets/packages/jstree/gruntfile.js
cabinets/static/cabinets/packages/jstree/demo/basic/index.html
cabinets/static/cabinets/packages/jstree/demo/filebrowser/file_sprite.png
cabinets/static/cabinets/packages/jstree/demo/filebrowser/data/root/index.html
cabinets/static/cabinets/packages/jstree/demo/filebrowser/data/root/asdf/New Text Document.txt
cabinets/static/cabinets/packages/jstree/demo/filebrowser/data/root/assets/ajax_nodes.html
cabinets/static/cabinets/packages/jstree/demo/filebrowser/data/root/assets/apple-touch-icon-precomposed.png
cabinets/static/cabinets/packages/jstree/demo/filebrowser/data/root/assets/docs.css
cabinets/static/cabinets/packages/jstree/demo/filebrowser/data/root/assets/docs.js
cabinets/static/cabinets/packages/jstree/demo/filebrowser/data/root/assets/favicon.ico
cabinets/static/cabinets/packages/jstree/demo/filebrowser/data/root/assets/html5.js
cabinets/static/cabinets/packages/jstree/demo/filebrowser/data/root/assets/jquery-1.10.2.min.js
cabinets/static/cabinets/packages/jstree/demo/filebrowser/data/root/assets/jquery.address-1.6.js
cabinets/static/cabinets/packages/jstree/demo/filebrowser/data/root/assets/respond.js
cabinets/static/cabinets/packages/jstree/demo/filebrowser/data/root/assets/vakata.js
cabinets/static/cabinets/packages/jstree/demo/filebrowser/data/root/assets/bootstrap/css/bootstrap-theme.css
cabinets/static/cabinets/packages/jstree/demo/filebrowser/data/root/assets/bootstrap/css/bootstrap-theme.min.css
mayan_cabinets-1.1.1.dist-info/DESCRIPTION.rst
mayan_cabinets-1.1.1.dist-info/METADATA
mayan_cabinets-1.1.1.dist-info/RECORD
mayan_cabinets-1.1.1.dist-info/WHEEL
mayan_cabinets-1.1.1.dist-info/metadata.json
mayan_cabinets-1.1.1.dist-info/top_level.txt
