Metadata-Version: 2.0
Name: mayan-cabinets
Version: 1.1.1
Summary: Multi level document hierachy app for Mayan EDMS.
Home-page: https://gitlab.com/mayan-edms/cabinets
Author: Roberto Rosario
Author-email: roberto.rosario@mayan-edms.com
License: Apache 2.0
Platform: any
Classifier: Development Status :: 5 - Production/Stable
Classifier: Environment :: Web Environment
Classifier: Framework :: Django
Classifier: Intended Audience :: End Users/Desktop
Classifier: License :: OSI Approved :: Apache Software License
Classifier: Natural Language :: English
Classifier: Operating System :: POSIX
Classifier: Programming Language :: Python
Requires-Dist: django-mptt (==0.8.7)
